fractal_task_tools/__init__.py
fractal_task_tools/_args_schemas.py
fractal_task_tools/_cli.py
fractal_task_tools/_cli_tools.py
fractal_task_tools/_create_manifest.py
fractal_task_tools/_deepdiff.py
fractal_task_tools/_descriptions.py
fractal_task_tools/_package_name_tools.py
fractal_task_tools/_pydantic_generatejsonschema.py
fractal_task_tools/_signature_constraints.py
fractal_task_tools/_task_arguments.py
fractal_task_tools/_task_docs.py
fractal_task_tools/_titles.py
fractal_task_tools/_union_types.py
fractal_task_tools/task_models.py
fractal_task_tools/task_wrapper.py
fractal_task_tools-0.2.1.dist-info/licenses/LICENSE
fractal_task_tools-0.2.1.dist-info/METADATA
fractal_task_tools-0.2.1.dist-info/WHEEL
fractal_task_tools-0.2.1.dist-info/entry_points.txt
fractal_task_tools-0.2.1.dist-info/top_level.txt
fractal_task_tools-0.2.1.dist-info/RECORD
