Metadata-Version: 2.4
Name: fractal-task-tools
Version: 0.2.1
Summary: Shared tools for Fractal tasks
Author-email: Tommaso Comparin <tommaso.comparin@exact-lab.it>
License: BSD-3-Clause
Project-URL: homepage, https://github.com/fractal-analytics-platform/fractal-task-tools
Project-URL: repository, https://github.com/fractal-analytics-platform/fractal-task-tools
Project-URL: changelog, https://github.com/fractal-analytics-platform/fractal-task-tools/blob/main/CHANGELOG.md
Requires-Python: <3.15,>=3.10
License-File: LICENSE
Requires-Dist: pydantic<=2.13.0,>=2.0.0
Requires-Dist: docstring-parser<=0.16,>=0.15
Requires-Dist: packaging
Provides-Extra: dev
Requires-Dist: bumpver==2024.1130; extra == "dev"
Requires-Dist: devtools==0.12.2; extra == "dev"
Requires-Dist: pytest<9.0.0,>=8.3.0; extra == "dev"
Requires-Dist: coverage<7.7.0,>=7.6.0; extra == "dev"
Requires-Dist: jsonschema>=4; extra == "dev"
Requires-Dist: requests<2.33.0,>2.32.0; extra == "dev"
Provides-Extra: docs
Requires-Dist: mkdocs==1.6.1; extra == "docs"
Requires-Dist: mkdocstrings[python]==0.30.0; extra == "docs"
Requires-Dist: mkdocs-material==9.6.15; extra == "docs"
Requires-Dist: mkdocs-gen-files==0.5.0; extra == "docs"
Requires-Dist: mkdocs-literate-nav==0.6.2; extra == "docs"
Requires-Dist: mkdocs-section-index==0.3.10; extra == "docs"
Requires-Dist: mkdocs-include-markdown-plugin==7.1.8; extra == "docs"
Dynamic: license-file
